README.md
setup.cfg
setup.py
probability_distributions_RanaMK/Binomialdistribution.py
probability_distributions_RanaMK/Gaussiandistribution.py
probability_distributions_RanaMK/Generaldistribution.py
probability_distributions_RanaMK/__init__.py
probability_distributions_RanaMK.egg-info/PKG-INFO
probability_distributions_RanaMK.egg-info/SOURCES.txt
probability_distributions_RanaMK.egg-info/dependency_links.txt
probability_distributions_RanaMK.egg-info/not-zip-safe
probability_distributions_RanaMK.egg-info/top_level.txt