Metadata-Version: 1.0
Name: probability-distributions-RanaMK
Version: 0.1
Summary: Gaussian and binomial distributions
Home-page: UNKNOWN
Author: Rana Kamel
Author-email: rana.mahmoudkamel@hotmail.com
License: UNKNOWN
Platform: UNKNOWN
